{
  "id": 1366237,
  "title": "",
  "slug": "582neot-26-rue-de-montevideo-13006-marseille-6eme-arrondissement-france",
  "permalink": "https://www.immobiliere-pujol.fr/annonces/582neot-26-rue-de-montevideo-13006-marseille-6eme-arrondissement-france/",
  "status": "closed",
  "date": "2026-02-12 20:13:16",
  "referenceAgence": "582neot",
  "typeAnnonce": "L",
  "termine": "Terminé",
  "adresse": "26 Rue De Montevideo, 13006, Marseille 6eme Arrondissement, France",
  "prix": 990,
  "charges": 48,
  "honoraires": "828.25",
  "garantie": "942",
  "surface": 63.13,
  "surfaceTerrain": 63.13,
  "nbPieces": 3,
  "nbChambres": 2,
  "meuble": false,
  "dpeNote": "d",
  "dpeValeur": "211",
  "gesNote": "B",
  "gesValeur": "8",
  "typeChauffage": "10240",
  "libelle": "Appartement T3",
  "descriptif": "Secteur Vauban - Agréable appartement Type 3 joliment rénové et calme de 63m² avec cave  situé au 26 rue Montevideo dans le 6e . L'appartement se trouve au rez-de-chaussée dans l'immeuble mais celui-ci est surélevé par rapport à la rue Montévidéo  équivalent à une 1er étage depuis la rue . Seule une fenêtre du séjour (avec film protecteur  ) donne sur l'entrée de l'immeuble , toutes les autres ne sont pas visibles et sont à un niveau de 1er étage par rapport aux rues qui entourent l'immeuble.  La résidence est très calme, très bien entretenue et fermée par un portillon sécurisé.<BR><BR>Cet appartement lumineux se compose : d'une grande pièce de vie de 34m² avec cuisine ouverte et équipée (four, plaques, réfrigérateur, congélateur, lave-vaisselle), de rangements dans l'entrée, d'une première chambre avec rangements et espace dressing, d'une seconde chambre très lumineuse, d'une salle d'eau avec douche à l'italienne et arrivée d'eau pour lave-linge, ainsi que de toilettes séparées.  L'appartement est équipé d'une alarme .<BR><BR>À proximité immédiate des commerces, écoles et transports en commun (bus 18, 19, 21, 41, 74, 81, métro M1 estrangin et proche de Castellane lignes M1 et M2, tramway T3).<BR><BR>Prévoir la taxe pour l'enlèvement des ordures ménagères en plus du loyer de 40&euro;/mois.<BR><BR>Visite vidéo disponible sur cette annonce ou en copiant ce lien : https://youtu.be/BinUA2pTQ-Q<BR><BR>Appartement avec un Diagnostic de Performance Énergétique classe : D<BR>Montant estimé des dépenses annuelles d'énergie pour un usage standard : entre 1260&euro; et 1750&euro; par an. Prix moyens des énergies indexés sur les années 2021, 2022, 2023 (abonnements compris).<BR><BR>Chauffage individuel électrique.<BR>Eau chaude individuelle électrique.<BR><BR>Les informations sur les risques auxquels ce bien est exposé sont disponibles sur le site Géorisques : www.georisques.gouv.fr<BR>.<BR><BR>IMPORTANT : Pour toute demande d'information ou pour déposer votre dossier, merci de nous envoyer un mail depuis l'annonce. Vous recevrez alors un formulaire à remplir. À réception, nous ne manquerons pas de revenir vers vous.<BR><BR>Le gestionnaire de cet appartement est Lola .",
  "photos": [
    "https://www.immobiliere-pujol.fr/content/uploads/2026/02/1-2151.jpg",
    "https://photos.ubiflow.net/132582/513242501/photos/1.jpg?SITE_PRIVE_IMMOBILIERE_PUJOL_5813289726_20260304184626",
    "https://photos.ubiflow.net/132582/513242501/photos/2.jpg?SITE_PRIVE_IMMOBILIERE_PUJOL_5813289726_20260304184626",
    "https://photos.ubiflow.net/132582/513242501/photos/3.jpg?SITE_PRIVE_IMMOBILIERE_PUJOL_5813289726_20260304184626",
    "https://photos.ubiflow.net/132582/513242501/photos/4.jpg?SITE_PRIVE_IMMOBILIERE_PUJOL_5813289726_20260304184626",
    "https://photos.ubiflow.net/132582/513242501/photos/5.jpg?SITE_PRIVE_IMMOBILIERE_PUJOL_5813289726_20260304184626",
    "https://photos.ubiflow.net/132582/513242501/photos/6.jpg?SITE_PRIVE_IMMOBILIERE_PUJOL_5813289726_20260304184626",
    "https://photos.ubiflow.net/132582/513242501/photos/7.jpg?SITE_PRIVE_IMMOBILIERE_PUJOL_5813289726_20260304184626",
    "https://photos.ubiflow.net/132582/513242501/photos/8.jpg?SITE_PRIVE_IMMOBILIERE_PUJOL_5813289726_20260304184626"
  ],
  "contactAAfficher": "loladertomassian@immobiliere-pujol.fr",
  "seoTitle": "Secteur Vauban - Agréable appartement Type 3 joliment rénové et calme de 63m² avec cave  situé au 26 rue Montevideo dans le 6e . L'appartement se trouve au rez-de-chaussée dans l'immeuble mais c…",
  "seoDescription": "Appartement T3 à louer, 26 Rue De Montevideo, 13006, Marseille 6eme Arrondissement, France"
}
