{
  "id": 88367,
  "title": "",
  "slug": "l000731-16-bd-garibaldi-canebiere-13001",
  "permalink": "https://www.immobiliere-pujol.fr/annonces/l000731-16-bd-garibaldi-canebiere-13001/",
  "status": "closed",
  "date": "2017-10-30 20:11:43",
  "referenceAgence": "L000731",
  "typeAnnonce": "L",
  "typeBien": "appartement",
  "termine": "Terminé",
  "adresse": "16 BD GARIBALDI",
  "codePostal": "13001",
  "ville": "MARSEILLE",
  "quartier": "CANEBIERE",
  "prix": 590.0,
  "charges": 40.0,
  "honoraires": "369",
  "garantie": "550",
  "surface": 32.0,
  "surfaceTerrain": 0.0,
  "nbPieces": 2,
  "etage": "4",
  "nbEtages": "0",
  "dpeNote": "d",
  "dpeValeur": "204",
  "gesValeur": "9",
  "typeChauffage": "10240",
  "libelle": "Appartement 2 pi&egrave;ces",
  "descriptif": "Type 2 r&eacute;nov&eacute; d'environ 32 m2 avec terrasse ensoleill&eacute;e situ&eacute; au 4e et dernier &eacute;tage sans ascenseur du 16 rue Garibaldi 13001 Marseille, &agrave; proximit&eacute; de l'universit&eacute; Paul C&eacute;zanne.<BR>L'appartement se compose : d'un s&eacute;jour avec un coin cuisine donnant sur une agr&eacute;able terrasse ensoleill&eacute;e donnant sur l'arri&egrave;re de l'immeuble, d'une chambre avec placard, d'une salle d'eau avec toilettes.<BR>Chauffage &eacute;lectrique.<BR>Provision mensuelle sur taxe d'ordures m&eacute;nag&egrave;res: 10&euro;<BR>Cette location se trouve &agrave; proximit&eacute; de nombreux commerces, boutiques, grands magasins, des bus, du tramway, du m&eacute;tro et du centre ville.<BR>Plus de renseignements sur les commodit&eacute;s du quartier sur note site.<BR>Disponible &agrave; compter du 25 D&eacute;cembre 2015<BR>Immobiilere Pujol  04 91 37 38 32 / 04 91 37 38 25",
  "dateDisponibilite": "25/12/2015",
  "contactAAfficher": "IMMOBILIERE PUJOL",
  "telephoneAAfficher": "04.91.37.38.32",
  "emailAAfficher": "corinne@immobiliere-pujol.fr"
}