{
  "id": 87212,
  "title": "LO12400003_D985",
  "slug": "l000685-175-rue-dendoume-endoume-13007",
  "permalink": "https://www.immobiliere-pujol.fr/annonces/l000685-175-rue-dendoume-endoume-13007/",
  "status": "closed",
  "date": "2017-10-30 20:08:51",
  "referenceAgence": "L000685",
  "typeAnnonce": "L",
  "typeBien": "appartement",
  "termine": "Terminé",
  "adresse": "175 Rue D'endoume, Endoume, 13007, Marseille, France",
  "codePostal": "13007",
  "ville": "MARSEILLE",
  "quartier": "ENDOUME",
  "prix": 500.0,
  "charges": 40.0,
  "honoraires": "468",
  "garantie": "460",
  "surface": 40.0,
  "surfaceTerrain": 36.0,
  "nbPieces": 2,
  "nbChambres": 1,
  "etage": "1",
  "nbEtages": "0",
  "coupDeCoeur": false,
  "dpeNote": "d",
  "dpeValeur": "197",
  "gesNote": "D",
  "gesValeur": "26",
  "typeChauffage": "8704",
  "libelle": "Appartement T2",
  "descriptif": "Endoume, T2 de 36m2 avec petite vue mer situé au 1er étage du 175 rue d''endoume dans le 13007.<BR>L'appartement se compose :  d'un hall d'entrée, d'une cuisine aménagée et équipée ouverture sur le séjour, d'une chambre, d'une salle de bains avec les toilettes.<BR>Chauffage individuel au gaz<BR>Situé à proximité de tous les commerces de la Rue d'Endoume, arrêt de bus en bas de l'immeuble et proche du centre Ville à pied.<BR>Prévoir en sus 10€/mois pour la taxe d'ordures ménagères.<BR>IMMOBILIERE PUJOL 04.91.37.33.60",
  "dateDisponibilite": "09/08/2014",
  "contactAAfficher": "ines@immobiliere-pujol.fr",
  "telephoneAAfficher": "04.91.37.38.21",
  "emailAAfficher": "nicolearnoux@immobiliere-pujol.fr",
  "seoTitle": "Endoume, T2 de 36m2 avec petite vue mer situé au 1er étage du 175 rue d''endoume dans le 13007.L'appartement se compose :  d'un hall d'entrée, d'une cuisine aménagée et équipée ouverture sur le…",
  "seoDescription": "Appartement T2 à louer, 175 Rue D'endoume, Endoume, 13007, Marseille, France",
  "photos": [
    "https://pub-a37eed540afe4dc9b4479da74ba265e1.r2.dev/2017/11/LO12400003_D985.jpg"
  ]
}