{
  "id": 53644,
  "title": "",
  "slug": "l000147-63-bd-saint-jean-capelette-13010",
  "permalink": "https://www.immobiliere-pujol.fr/annonces/l000147-63-bd-saint-jean-capelette-13010/",
  "status": "closed",
  "date": "2017-10-30 19:54:44",
  "referenceAgence": "L000147",
  "typeAnnonce": "L",
  "typeBien": "appartement",
  "termine": "Terminé",
  "adresse": "63 BD SAINT JEAN",
  "codePostal": "13010",
  "ville": "MARSEILLE",
  "quartier": "CAPELETTE",
  "prix": 790.0,
  "charges": 90.0,
  "honoraires": "290",
  "garantie": "700",
  "surface": 61.0,
  "surfaceTerrain": 0.0,
  "nbPieces": 3,
  "etage": "2",
  "nbEtages": "0",
  "dpeNote": "c",
  "dpeValeur": "0",
  "gesValeur": "0",
  "typeChauffage": "10240",
  "libelle": "Appartement 3 pi&egrave;ces",
  "descriptif": "Location appartement T3 r&eacute;cent  avec parking, garage et terrasse situ&eacute; au 2e &eacute;tage dans la r&eacute;sidence Villa St Jean au 63 Bd Saint Jean 13010 Marseille.<BR>Ce type 3 se compose : d'une entr&eacute;e, d'une cuisine am&eacute;nag&eacute;e, d'un s&eacute;jour donnant sur une terrasse de 9m2, de deux chambres, de placards/penderies,  d'une salle de bains, de toilettes s&eacute;par&eacute;es. L'appartement dispose &eacute;galement d'une place de parking au rez-de-chauss&eacute;e et d'un garage/ box au 1er sous-sol.<BR>Chauffage et eau chaude individuels &eacute;lectriques<BR>Cette location est bien plac&eacute;e, &agrave; c&ocirc;t&eacute; des commerces de quartier, des bus et des &eacute;coles. Pour plus de d&eacute;tails sur le quartier, n'h&eacute;sitez pas &agrave; consulter notre site internet.<BR>Appartement disponible au 18 Août 2014<BR>IMMOBILIERE PUJOL 04.91.37.38.32 ou 04.91.37.38.25",
  "dateDisponibilite": "18/08/2014",
  "contactAAfficher": "IMMOBILIERE PUJOL",
  "telephoneAAfficher": "04.91.37.38.32",
  "emailAAfficher": "corinne@immobiliere-pujol.fr",
  "photos": [
    "https://pub-a37eed540afe4dc9b4479da74ba265e1.r2.dev/2017/06/LO29130001_BC15.jpg"
  ]
}