{
  "id": 256451,
  "title": "LO04300002_E74D13020503",
  "slug": "l000246-63-boulevard-saint-jean-capelette-13010-marseille-france",
  "permalink": "https://www.immobiliere-pujol.fr/annonces/l000246-63-boulevard-saint-jean-capelette-13010-marseille-france/",
  "status": "closed",
  "date": "2019-08-22 20:13:00",
  "referenceAgence": "L000246",
  "typeAnnonce": "L",
  "termine": "Terminé",
  "adresse": "63 Boulevard Saint Jean, Capelette, 13010, Marseille, France",
  "prix": 760.0,
  "charges": 80.0,
  "honoraires": "754",
  "garantie": "680",
  "surface": 58.0,
  "surfaceTerrain": 58.0,
  "nbPieces": 3,
  "nbChambres": 2,
  "etage": "1",
  "nbEtages": "0",
  "coupDeCoeur": false,
  "dpeNote": "d",
  "gesNote": "D",
  "typeChauffage": "10240",
  "libelle": "Appartement T3",
  "descriptif": "Quartier la Capelette 13010, résidence Villa st jean 63 bd Saint Jean, type 3 avec terrasse de 14m2 et garage double.<BR>Appartement situé au 1er étage avec ascenseur, composé d'un hall, cuisine séparée aménagée en placards et électroménagers (four, hotte et plaque électrique), séjour, donnant sur la terrasse, deux chambres, un coin nuit, wc séparé, salle de bains.<BR>Chauffage et eau chaude invidivuels électriques<BR>Prévoir en plus du loyer la taxe ordures ménagères d'un montant de 30 euros par mois<BR>IMMOBILIERE PUJOL 04.91.37.38.32.",
  "contactAAfficher": "corinne@immobiliere-pujol.fr",
  "seoTitle": "Quartier la Capelette 13010, résidence Villa st jean 63 bd Saint Jean, type 3 avec terrasse de 14m2 et garage double.Appartement situé au 1er étage avec ascenseur, composé d'un hall, cuisine sépa…",
  "seoDescription": "Appartement T3 à louer, 63 Boulevard Saint Jean, Capelette, 13010, Marseille, France",
  "photos": [
    "https://www.immobiliere-pujol.fr/content/uploads/2019/09/LO04300002_E74D13020503.jpg"
  ]
}