{
  "id": 87597,
  "title": "LO11920009_EC9D10572899",
  "slug": "l001548-65-rue-belle-de-mai-belle-de-mai-13003",
  "permalink": "https://www.immobiliere-pujol.fr/annonces/l001548-65-rue-belle-de-mai-belle-de-mai-13003/",
  "status": "closed",
  "date": "2017-10-30 20:09:51",
  "referenceAgence": "L001548",
  "typeAnnonce": "L",
  "typeBien": "appartement",
  "termine": "Terminé",
  "adresse": "65 Rue Belle De Mai, Belle De Mai, 13003, MARSEILLE, France",
  "codePostal": "13003",
  "ville": "MARSEILLE",
  "quartier": "BELLE DE MAI",
  "prix": 485.0,
  "charges": 35.0,
  "honoraires": "424.71",
  "garantie": "450",
  "surface": 30.0,
  "surfaceTerrain": 32.67,
  "nbPieces": 1,
  "nbChambres": 1,
  "etage": "2",
  "nbEtages": "0",
  "meuble": false,
  "coupDeCoeur": false,
  "dpeNote": "d",
  "dpeValeur": "247",
  "gesNote": "B",
  "gesValeur": "7",
  "typeChauffage": "10240",
  "libelle": "Appartement T1",
  "descriptif": "Appartement lumineux et en très bon état de Type 1/2 de 32m2, offrant la possibilté de créer un espace nuit et un espace salon dans la même pièce (à séparer par rideau ou meuble haut comme suggéré sur les photos) . Cette location se situe au 2e étage sans ascenseur au 65, rue Belle de Mai dans le 3e arrondissement.<BR>L'appartement se compose : d'un séjour avec un espace cuisine ouverte et une alcôve pouvant accueillir un coin nuit, une salle d'eau avec les toilettes.<BR>Le chauffage est électrique et les fenêtres en PVC double vitrage.<BR>Cette location se trouve à côté des commerces et est desservie par le métro St Charles ou Désirée Clary à 10mn à pieds et les bus 33,34 et 49.<BR>Prévoir en plus du loyer la taxe d'ordure ménagère de 16€/mois<BR>Visite virtuelle disponible sur cette annonce ou en copiant ce lien : https://tour.previsite.com/48F130AA-2952-EA7C-03D8-EE2C6E25ABC9<BR>Appartement avec un Diagnostic de Performance Energétique classe D . Montant moyen estimé des dépenses annuelles d'énergie pour un usage standard (abonnement compris), établi à partir des prix de l'énergie du 01 janvier 2021 entre 540 et 770 euros par an.<BR>Les informations sur les risques auxquels ce bien est exposé sont disponibles sur le site Géorisques : www.georisques.gouv.fr<BR>Disponible immédiatement<BR>IMPORTANT :  Pour toute demande d'information ou pour déposer votre dossier, merci de nous envoyez un mail depuis l'annonce .<BR>La gestionnaire de cet appartement est Corinne",
  "dateDisponibilite": "28/02/2015",
  "contactAAfficher": "corinne@immobiliere-pujol.fr",
  "telephoneAAfficher": "04.91.37.38.32",
  "emailAAfficher": "corinne@immobiliere-pujol.fr",
  "seoTitle": "Appartement lumineux et en très bon état de Type 1/2 de 32m2, offrant la possibilté de créer un espace nuit et un espace salon dans la même pièce (à séparer par rideau ou meuble haut comme sug…",
  "seoDescription": "Appartement T1 à louer, 65 Rue Belle De Mai, Belle De Mai, 13003, MARSEILLE, France",
  "photos": [
    "https://www.immobiliere-pujol.fr/content/uploads/2023/06/LO11920009_EC9D10572899.jpg",
    "https://www.immobiliere-pujol.fr/content/uploads/2023/06/LO11920009_EDE610572931.jpg",
    "https://www.immobiliere-pujol.fr/content/uploads/2023/06/LO11920009_EF9D10572976.jpg"
  ]
}