{
  "id": 84055,
  "title": "",
  "slug": "l001218-129-bd-francoise-duparc-chartreux-13004",
  "permalink": "https://www.immobiliere-pujol.fr/annonces/l001218-129-bd-francoise-duparc-chartreux-13004/",
  "status": "closed",
  "date": "2017-10-30 20:01:25",
  "referenceAgence": "L001218",
  "typeAnnonce": "L",
  "typeBien": "Appartement",
  "termine": "Terminé",
  "adresse": "129 BD FRANCOISE DUPARC",
  "codePostal": "13004",
  "ville": "MARSEILLE",
  "quartier": "CHARTREUX",
  "prix": 650.0,
  "charges": 80.0,
  "honoraires": "691",
  "garantie": "570",
  "surface": 40.0,
  "surfaceTerrain": 0.0,
  "nbPieces": 2,
  "etage": "3",
  "nbEtages": "0",
  "dpeNote": "d",
  "dpeValeur": "0",
  "gesValeur": "0",
  "typeChauffage": "4096",
  "libelle": "Appartement 2 pi&egrave;ces",
  "descriptif": "QUARTIER CHARTREUX : T2 de 40 m&sup2; au 3e &eacute;tage avec ascenseur du 129 Boulevard Fran&ccedil;oise Duparc 1304 Marseille. L'appartement a &eacute;t&eacute; enti&egrave;rement repeint, il comprend un hall d'entr&eacute;e avec placard de rangement, une cuisine am&eacute;nag&eacute;e, un s&eacute;jour, une chambre, une salle de bains et un WC ind&eacute;pendant.<BR>L'appartement est disponible imm&eacute;diatement.<BR>Contact Immobili&egrave;re PUJOL au 04.91.37.38.26 ou 04.91.37.38.25",
  "dateDisponibilite": "01/06/2013",
  "contactAAfficher": "IMMOBILIERE PUJOL",
  "telephoneAAfficher": "04.91.37.38.26",
  "emailAAfficher": "patriciabof@immobiliere-pujol.fr"
}