{
  "id": 440220,
  "title": "LO39990405_D2DD08505376",
  "slug": "l002640-80-boulevard-barry-13013-marseille-france",
  "permalink": "https://www.immobiliere-pujol.fr/annonces/l002640-80-boulevard-barry-13013-marseille-france/",
  "status": "closed",
  "date": "2021-09-28 20:44:54",
  "referenceAgence": "L002640",
  "typeAnnonce": "L",
  "termine": "Terminé",
  "adresse": "80 Boulevard Barry, 13013, Marseille, France",
  "prix": 790.0,
  "charges": 100.0,
  "honoraires": "380",
  "garantie": "690",
  "surface": 57.69,
  "surfaceTerrain": 57.69,
  "nbPieces": 3,
  "nbChambres": 0,
  "etage": "4",
  "nbEtages": "0",
  "meuble": false,
  "coupDeCoeur": false,
  "dpeNote": "a",
  "dpeValeur": "46",
  "gesNote": "B",
  "gesValeur": "10",
  "typeChauffage": "4608",
  "libelle": "Appartement T3",
  "descriptif": "Secteur Saint Just, type 3 avec terrasse et emplacement voiture dans résidence récente JARDINS DES ARTS située 80 Bd Barry 13009 Marseille.<BR>Cet appartement lumineux  d'une surface de 58m² se situe au 4ème et dernier étage d'un immeuble avec ascenseur.Il se compose d'une cuisine ouverte sur le séjour, aménagée et équipée (plaques de cuisson, hotte aspirante , refrigirateur )<BR>- de deux chambres<BR>- d'une salle de bain avec baignoire<BR>Chauffage et eau chaude collectif<BR>Cette location dispose d'une place de parking en sous sol.<BR>L'appartement est soumis au dispositif  PINEL<BR>Prévoir en sus du loyer, une provision mensuelle pour la Taxe d’Ordures Ménagères : 35,00 €<BR>Disponible immédiatement.<BR>Visitez ce bien depuis chez vous dans un premier temps grâce à la visite virtuelle disponible sur cette annonce ou sur demande auprès du contact de l'annonce:<BR>https://tour.previsite.com/80DFF586-663C-5128-CD17-60ED37B93679<BR>IMMOBILIERE PUJOL location1@immobilere-pujol.fr",
  "contactAAfficher": "carolinefabre@immobiliere-pujol.fr",
  "seoTitle": "Secteur Saint Just, type 3 avec terrasse et emplacement voiture dans résidence récente JARDINS DES ARTS située 80 Bd Barry 13009 Marseille.Cet appartement lumineux  d'une surface de 58m² se situe …",
  "seoDescription": "Appartement T3 à louer, 80 Boulevard Barry, 13013, Marseille, France",
  "photos": [
    "https://www.immobiliere-pujol.fr/content/uploads/2021/09/LO39990405_D2DD08505376.jpg",
    "https://www.immobiliere-pujol.fr/content/uploads/2021/09/LO39990405_76EE08513576.jpg",
    "https://www.immobiliere-pujol.fr/content/uploads/2021/09/LO39990405_9B4F08514508.jpg",
    "https://www.immobiliere-pujol.fr/content/uploads/2021/09/LO39990405_BC9408515359.jpg",
    "https://www.immobiliere-pujol.fr/content/uploads/2021/09/LO39990405_D4E008515981.jpg"
  ]
}