{
  "id": 228284,
  "title": "LO12370005_F22E.JPG",
  "slug": "l002067-location-appartement-13005-marseille",
  "permalink": "https://www.immobiliere-pujol.fr/annonces/l002067-location-appartement-13005-marseille/",
  "status": "closed",
  "date": "2018-04-11 08:29:47",
  "referenceAgence": "L002067",
  "typeAnnonce": "L",
  "typeBien": "Appartement",
  "termine": "Terminé",
  "adresse": "134 Chemin Saint Jean Du Désert, Saint Pierre, 13005, Marseille, France",
  "codePostal": "13005",
  "ville": "MARSEILLE",
  "quartier": "SAINT PIERRE",
  "prix": 485,
  "charges": 15,
  "honoraires": "494",
  "garantie": "470",
  "surface": 38,
  "surfaceTerrain": 38,
  "nbPieces": 2,
  "nbChambres": 1,
  "nbSallesBain": 0,
  "nbSallesEau": 1,
  "nbWC": 1,
  "etage": "2",
  "nbEtages": "0",
  "meuble": false,
  "coupDeCoeur": false,
  "ascenseur": false,
  "cave": false,
  "parking": "0",
  "garage": "0",
  "terrasse": false,
  "piscine": false,
  "dpeNote": "e",
  "dpeValeur": "296",
  "gesNote": "C",
  "gesValeur": "16",
  "typeChauffage": "10240",
  "libelle": "Appartement T2",
  "descriptif": "Secteur Saint-Pierre - Appartement de type 2 situé au 134 rue saint jean du desert 13005 Marseille.<BR>Dans un immeuble marseillais bourgeois, à 200m du tramway, métro, hopital de la timone, écoles de médecines etc.<BR>Cet appartement, au 2éme étage sans ascenseur se compose d'un hall, une cuisine aménagée ouverte sur le séjour, une chambre avec de multiples rangements, une salle d'eau avec wc.<BR>Chauffage et eau chaude individuels electriques.<BR>Il sera disponible le 02/11/2021.<BR>Immobiliere PUJOL",
  "dateDisponibilite": "19/02/2018",
  "contactAAfficher": "severine@immobiliere-pujol.fr",
  "telephoneAAfficher": "04 91 37 38 21",
  "emailAAfficher": "nicole@immobiliere-pujol.fr",
  "seoTitle": "Secteur Saint-Pierre - Appartement de type 2 situé au 134 rue saint jean du desert 13005 Marseille.Dans un immeuble marseillais bourgeois, à 200m du tramway, métro, hopital de la timone, écoles de…",
  "seoDescription": "Appartement T2 à louer, 134 Chemin Saint Jean Du Désert, Saint Pierre, 13005, Marseille, France",
  "photos": [
    "https://pub-a37eed540afe4dc9b4479da74ba265e1.r2.dev/2021/10/LO12370005_F22E.jpg",
    "https://pub-a37eed540afe4dc9b4479da74ba265e1.r2.dev/2018/03/LO12370005_F22E.jpg",
    "https://pub-a37eed540afe4dc9b4479da74ba265e1.r2.dev/2018/03/LO12370005_2390.jpg",
    "https://pub-a37eed540afe4dc9b4479da74ba265e1.r2.dev/2018/03/LO12370005_61E2.jpg",
    "https://pub-a37eed540afe4dc9b4479da74ba265e1.r2.dev/2018/03/LO12370005_704A.jpg",
    "https://pub-a37eed540afe4dc9b4479da74ba265e1.r2.dev/2018/03/LO12370005_81A1.jpg",
    "https://pub-a37eed540afe4dc9b4479da74ba265e1.r2.dev/2018/03/LO12370005_9190.jpg"
  ]
}
