{
  "id": 477532,
  "title": "LO40190002_33D011584646",
  "slug": "l002700-205-avenue-du-prado-prado-13008-marseille-france",
  "permalink": "https://www.immobiliere-pujol.fr/annonces/l002700-205-avenue-du-prado-prado-13008-marseille-france/",
  "status": "closed",
  "date": "2022-01-26 21:49:57",
  "referenceAgence": "L002700",
  "typeAnnonce": "L",
  "termine": "Terminé",
  "adresse": "205 Avenue Du Prado, Prado, 13008, Marseille, France",
  "prix": 1155.0,
  "charges": 200.0,
  "honoraires": "380.00",
  "garantie": "855",
  "surface": 62.51,
  "surfaceTerrain": 62.51,
  "nbPieces": 3,
  "nbChambres": 2,
  "etage": "4",
  "nbEtages": "0",
  "meuble": false,
  "coupDeCoeur": true,
  "dpeNote": "b",
  "dpeValeur": "53",
  "gesNote": "B",
  "gesValeur": "10",
  "typeChauffage": "4608",
  "libelle": "Appartement T3",
  "descriptif": "Secteur Perier/ Prado - Appartement type 3 neuf climatisé de grand standing, avec terrasse exposée sud sans vis à vis avec parking situé dans la résidence neuve le 205 Prado.<BR>Cet appartement de 62,50 m² donne sur le Bd de Louvain et se trouve au 4e étage sur 5 avec ascenseur.<BR>Il se compose : d'un séjour de 28m² donnant sur une terrasse de 8,5m² plein sud sans vis à vis, d'une cuisine aménagée ouverte sur le séjour avec ilot central, de deux chambres dont une avec placards, d'une salle de bains avec double vasque, des toilettes séparées. Climatisation réversibles, place de parking privative indissociable comprise dans le loyer indiqué.<BR>Proches de toutes commodités : métro Rond Point du Prado et Périer (à 300m), des bus, L2 et tunnel Prado.<BR>A proximité de commerces, d'écoles, collègues et lycées.<BR>Appartement avec un Diagnostic de Performance Energétique classe B :  Montant estimé des dépenses annuelles d’énergie pour un usage standard : entre 211 et 285€ par an. Prix moyens des énergies indexés au 01/01/2021 (abonnement compris)<BR>Libre au 1er février 2022.<BR>Chauffage, eau chaude, eau froide collectifs compris dans les charges<BR>location soumise à plafond de ressources (loi pinel)<BR>Visitez ce bien depuis chez vous en copiant/ collant le lien ci-dessous dans votre barre de recherche :<BR>https://tour.previsite.com/F7383C2F-A782-0652-E3D1-50C79369111D?lead_capture=false<BR>Si cette annonce vous intéresse, merci de contacter Immobilière Pujol - Clémence RANSON à l'adresse suivante clemence@immobiliere-pujol.fr",
  "contactAAfficher": "clemence@immobiliere-pujol.fr",
  "seoTitle": "Secteur Perier/ Prado - Appartement type 3 neuf climatisé de grand standing, avec terrasse exposée sud sans vis à vis avec parking situé dans la résidence neuve le 205 Prado.Cet appartement de 62…",
  "seoDescription": "Appartement T3 à louer, 205 Avenue Du Prado, Prado, 13008, Marseille, France",
  "photos": [
    "https://pub-a37eed540afe4dc9b4479da74ba265e1.r2.dev/2022/02/LO40190002_33D011584646.jpg",
    "https://pub-a37eed540afe4dc9b4479da74ba265e1.r2.dev/2022/02/LO40190002_F8E11583717.jpg",
    "https://pub-a37eed540afe4dc9b4479da74ba265e1.r2.dev/2022/02/LO40190002_3FF611584957.jpg",
    "https://pub-a37eed540afe4dc9b4479da74ba265e1.r2.dev/2022/02/LO40190002_47A811585154.jpg",
    "https://pub-a37eed540afe4dc9b4479da74ba265e1.r2.dev/2022/02/LO40190002_61D911585824.jpg",
    "https://pub-a37eed540afe4dc9b4479da74ba265e1.r2.dev/2022/02/LO40190002_4E2111585319.jpg",
    "https://pub-a37eed540afe4dc9b4479da74ba265e1.r2.dev/2022/01/LO40190002_D06208380306.jpg",
    "https://pub-a37eed540afe4dc9b4479da74ba265e1.r2.dev/2022/01/LO40190002_F11A08381144.jpg"
  ]
}