{
  "id": 525438,
  "title": "LO41360002_C8FF09240366",
  "slug": "l002789-1-rue-joseph-clerissy-saint-jean-du-desert-13012-marseille-france",
  "permalink": "https://www.immobiliere-pujol.fr/annonces/l002789-1-rue-joseph-clerissy-saint-jean-du-desert-13012-marseille-france/",
  "status": "closed",
  "date": "2022-07-14 20:08:06",
  "referenceAgence": "L002789",
  "typeAnnonce": "L",
  "termine": "Terminé",
  "adresse": "1 Rue Joseph Clérissy, Saint-jean Du Desert, 13012, Marseille, France",
  "prix": 780.0,
  "charges": 85.0,
  "honoraires": "574.60",
  "garantie": "695",
  "surface": 44.2,
  "surfaceTerrain": 44.2,
  "nbPieces": 2,
  "nbChambres": 1,
  "etage": "2",
  "nbEtages": "0",
  "meuble": false,
  "coupDeCoeur": false,
  "dpeNote": "b",
  "dpeValeur": "54",
  "gesNote": "B",
  "gesValeur": "10",
  "typeChauffage": "4608",
  "libelle": "Appartement T2",
  "descriptif": "Les hauts de Clérissy 13012,  T2 neuf avec terrasse et parking situé au 2e étage sur l'intérieur au calme dans une belle résidence neuve avec ascenseur.<BR>Cet appartement de 44,2m² se compose : d'un séjour avec cuisine aménagée ouverte donnant sur  une terrasse sud de 10m² avec vue sur les pins, d'une chambre, d'une salle d'eau avec les toilettes, d'une entrée avec placard.<BR>Prévoir en plus du loyer la provision pour la taxe d'enlèvement des ordures ménagères de 20€/mois.<BR>Passage du tramway en bas de la résidence, commerces à pieds, sortie St Jean du désert L2 à 200m.<BR>Chauffage et eau chaude collectifs (compris dans les charges).<BR>Appartement avec un dispositif Pinel.<BR>Montant estimé des dépenses annuelles d’énergie pour un usage standard : entre 145 et 196 € par an Prix moyens des énergies indexés au 03/01/2021 (abonnement compris)<BR>Visite virtuelle disponible sur cet annonce ou en copiant ce lien :<BR>https://tour.previsite.com/7331ADEC-8695-8C51-FACD-3F551C2B9B65<BR>IMPORTANT, pour toute demande d'information ou pour déposer votre dossier, merci de nous envoyez un mail depuis l'annonce . Vous recevrez alors un formulaire à remplir. A réception, nous ne manquerons pas de revenir vers vous. La gestionnaire de cet appartement est Alexandra.",
  "contactAAfficher": "alexandralopez@immobiliere-pujol.fr",
  "seoTitle": "Les hauts de Clérissy 13012,  T2 neuf avec terrasse et parking situé au 2e étage sur l'intérieur au calme dans une belle résidence neuve avec ascenseur.Cet appartement de 44,2m² se compose : d'u…",
  "seoDescription": "Appartement T2 à louer, 1 Rue Joseph Clérissy, Saint-jean Du Desert, 13012, Marseille, France",
  "photos": [
    "https://www.immobiliere-pujol.fr/content/uploads/2022/08/LO41360002_C8FF09240366.jpg",
    "https://www.immobiliere-pujol.fr/content/uploads/2022/08/LO41360002_3F609241875.jpg",
    "https://www.immobiliere-pujol.fr/content/uploads/2022/08/LO41360002_D8C09242121.jpg",
    "https://www.immobiliere-pujol.fr/content/uploads/2022/08/LO41360002_155D09242320.jpg",
    "https://www.immobiliere-pujol.fr/content/uploads/2022/08/LO41360002_1E0909242542.jpg",
    "https://www.immobiliere-pujol.fr/content/uploads/2022/08/LO41360002_4F7E17592960.jpg"
  ]
}