{
  "id": 409589,
  "title": "LO37940001_3D9B18203036",
  "slug": "l002593-65-avenue-du-prado-prado-13006-marseille-france",
  "permalink": "https://www.immobiliere-pujol.fr/annonces/l002593-65-avenue-du-prado-prado-13006-marseille-france/",
  "status": "closed",
  "date": "2021-05-24 20:38:17",
  "referenceAgence": "L002593",
  "typeAnnonce": "L",
  "termine": "Terminé",
  "adresse": "65 Avenue Du Prado, Prado, 13006, MARSEILLE, France",
  "prix": 755.0,
  "charges": 35.0,
  "honoraires": "371.80",
  "garantie": "1440",
  "surface": 28.6,
  "surfaceTerrain": 28.6,
  "nbPieces": 2,
  "nbChambres": 1,
  "etage": "5",
  "nbEtages": "0",
  "meuble": true,
  "coupDeCoeur": true,
  "dpeNote": "c",
  "dpeValeur": "173",
  "gesNote": "A",
  "gesValeur": "5",
  "typeChauffage": "10240",
  "libelle": "Appartement T2",
  "descriptif": "Quartier Prado - Castellane - Appartement meublé de Type 2 avec balcon situé au 65 avenue du Prado, 13006 Marseille.<BR>Cet appartement de 28 m² au 5ème étage avec ascenseur entièrement rénové avec mobilier neuf composé d'un séjour/cuisine donnant sur un balcon, d'une salle d'eau avec machine à laver, d'une chambre fonctionnelle. L'appartement est au calme et sans vis à vis sur le côté de l'immeuble<BR>Montant de la taxe d'enlèvement des ordures ménagères 20 € (à régler en plus du loyer et des charges)<BR>A proximité des transports (métro, tramway et bus) et des commerces.<BR>Visitez ce bien depuis chez vous dans un premier temps grâce à la visite virtuelle disponible sur cette annonce ou sur demande auprès du contact de l'annonce<BR>https://tour.previsite.com/58C1040E-3E1E-CEE2-E6F0-092EFAF3BAA8<BR>Disponible à compter du 07.07.2023<BR>Diagnostic de performance énergétique de l’appartement : classe C<BR>Montant estimé des dépenses annuelles d’énergie pour un usage standard : entre 360.00€ et 560.00€ par an; Prix moyens des énergies indexés au 01/01/2021 (abonnement compris)<BR>Les informations sur les risques auxquels ce bien est exposé sont disponibles sur le site Géorisques : www.georisques.gouv.fr<BR>IMPORTANT :  Pour toute demande d'information ou pour déposer votre dossier, merci de nous envoyer un mail depuis l'annonce . Vous recevrez alors un formulaire à remplir. A réception, nous ne manquerons pas de revenir vers vous.<BR>La gestionnaire de cet appartement est Mélanie.",
  "contactAAfficher": "melanie@immobiliere-pujol.fr",
  "seoTitle": "Quartier Prado - Castellane - Appartement meublé de Type 2 avec balcon situé au 65 avenue du Prado, 13006 Marseille.Cet appartement de 28 m² au 5ème étage avec ascenseur entièrement rénové ave…",
  "seoDescription": "Appartement T2 à louer, 65 Avenue Du Prado, Prado, 13006, MARSEILLE, France",
  "photos": [
    "https://www.immobiliere-pujol.fr/content/uploads/2021/05/LO37940001_3D9B18203036.jpg",
    "https://www.immobiliere-pujol.fr/content/uploads/2021/05/LO37940001_B4AC18220638.jpg",
    "https://www.immobiliere-pujol.fr/content/uploads/2021/05/LO37940001_D82318221546.jpg",
    "https://www.immobiliere-pujol.fr/content/uploads/2021/05/LO37940001_ED9018222094.jpg",
    "https://www.immobiliere-pujol.fr/content/uploads/2021/05/LO37940001_FFA218222556.jpg",
    "https://www.immobiliere-pujol.fr/content/uploads/2021/05/LO37940001_163918223135.jpg"
  ]
}