{
  "id": 536740,
  "title": "LO41590001_F0D811364076",
  "slug": "l002802-23-rue-yves-lariven-timone-13005-marseille-france",
  "permalink": "https://www.immobiliere-pujol.fr/annonces/l002802-23-rue-yves-lariven-timone-13005-marseille-france/",
  "status": "closed",
  "date": "2022-08-02 20:06:46",
  "referenceAgence": "L002802",
  "typeAnnonce": "L",
  "termine": "Terminé",
  "adresse": "23 Rue Yves Lariven, Timone, 13005, MARSEILLE, France",
  "prix": 590.0,
  "charges": 50.0,
  "honoraires": "275.60",
  "garantie": "1080",
  "surface": 21.2,
  "surfaceTerrain": 21.2,
  "nbPieces": 1,
  "nbChambres": 0,
  "etage": "4",
  "nbEtages": "4",
  "meuble": true,
  "coupDeCoeur": false,
  "dpeNote": "d",
  "dpeValeur": "222",
  "gesNote": "B",
  "gesValeur": "8",
  "typeChauffage": "10240",
  "libelle": "Appartement T1",
  "descriptif": "Agréable studio meublé de 21m² avec balcon au calme situé au 4e et dernier étage avec ascenseur au 23 Rue Yves Lariven à 5mn des facs de la Timone et du métro.<BR>Cet appartement se compose : d'une pièce à vivre avec lit simple ou double, d'un balcon au calme et sans vis à vis, d'une petite cuisine équipée (plaque électrique, frigo, congélateur, micro-ondes), d'une salle d'eau avec toillettes .<BR>A côté des facs de la Timone, des commerces de quartier du bd baille et de toutes les commodités.<BR>Visite virtuelle disponible sur cette annonce ou en copiant ce lien :<BR>https://tour.previsite.com/306452E2-84C8-9444-25DD-45C759E1ADA2?lead_capture=false<BR>Prévoir la taxe d'ordures ménagère de 12€/mois en plus du loyer.<BR>Appartement avec un Diagnostic de Performance Energétique classe D :  Montant moyen estimé des dépenses annuelles d'énergie pour un usage standard, établi à partir des prix de l'énergie de l'année 2015: 315€<BR>Les informations sur les risques auxquels ce bien est exposé sont disponibles sur le site Géorisques : www.georisques.gouv.fr.<BR>IMPORTANT :  Pour toute demande d'information ou pour déposer votre dossier, merci de nous envoyez un mail depuis l'annonce . Vous recevrez alors un formulaire à remplir. A réception, nous ne manquerons pas de revenir vers vous.<BR>La gestionnaire de cet appartement est Florian.",
  "contactAAfficher": "florian@immobiliere-pujol.fr",
  "seoTitle": "Agréable studio meublé de 21m² avec balcon au calme situé au 4e et dernier étage avec ascenseur au 23 Rue Yves Lariven à 5mn des facs de la Timone et du métro.Cet appartement se compose : d'une…",
  "seoDescription": "Appartement T1 à louer, 23 Rue Yves Lariven, Timone, 13005, MARSEILLE, France",
  "photos": [
    "https://pub-a37eed540afe4dc9b4479da74ba265e1.r2.dev/2022/08/LO41590001_F0D811364076.jpg",
    "https://pub-a37eed540afe4dc9b4479da74ba265e1.r2.dev/2022/08/LO41590001_299D11365530.jpg",
    "https://pub-a37eed540afe4dc9b4479da74ba265e1.r2.dev/2022/08/LO41590001_365F11365857.jpg",
    "https://pub-a37eed540afe4dc9b4479da74ba265e1.r2.dev/2022/08/LO41590001_470A11370284.jpg"
  ]
}