{
  "id": 807342,
  "title": "",
  "slug": "ljvpa120009355-13008-marseille-france",
  "permalink": "https://www.immobiliere-pujol.fr/annonces/ljvpa120009355-13008-marseille-france/",
  "status": "closed",
  "date": "2024-06-20 20:04:57",
  "referenceAgence": "LJVPA120009355",
  "typeAnnonce": "V",
  "termine": "Terminé",
  "adresse": "13008, Marseille, France",
  "prix": 22220,
  "charges": 8.33,
  "honoraires": "0.00",
  "garantie": "0",
  "surface": 14.54,
  "surfaceTerrain": 14.54,
  "nbPieces": 0,
  "nbChambres": 0,
  "etage": "0",
  "nbEtages": "0",
  "descriptif": "Exclusivité, proche Perier, dans la résidence récente et sécurisée « 205 Prado » (2022) , située au 205 avenue du Prado, 4 Parking Moto, en sous-sol.<br> Dimensions : 14,54m2 (de 2,15 m à 3,11m * 1,22m).<br> Mandat 6055. Charges annuelles 100 EUR. Taxe Foncière: 162 EUR. Honoraires à la charge du vendeur. Copropriété de 164 lots d'habitation. Pas de procédures à l'encontre du syndicat des copropriétaires. Les informations sur les risques auxquels ce bien est exposé sont disponibles sur le site Géorisques : www.georisques.gouv.fr<br> IMMOBILIERE PUJOL / Julia LAURON 06 58 44 28 28",
  "photos": [
    "https://pub-a37eed540afe4dc9b4479da74ba265e1.r2.dev/2024/06/photo_51428bce596a4f20c416aaee80bcaf85-90.jpg",
    "https://immopujol.staticlbi.com/wa/images/biens/1/937760717d8bb06d969a251d7857bdc4/photo_51428bce596a4f20c416aaee80bcaf85.jpg",
    "https://immopujol.staticlbi.com/wa/images/biens/1/937760717d8bb06d969a251d7857bdc4/photo_0c7bbec5ffb86db4ae6e3ae13e0b5f89.jpg",
    "https://immopujol.staticlbi.com/wa/images/biens/1/937760717d8bb06d969a251d7857bdc4/photo_3506cf1d5e7e1685ef34a1b6c4e7a698.jpg"
  ],
  "contactAAfficher": "julia@immobiliere-pujol.fr",
  "seoTitle": "Exclusivité, proche Perier, dans la résidence récente et sécurisée « 205 Prado » (2022) , située au 205 avenue du Prado, 4 Parking Moto, en sous-sol. Dimensions : 14,54m2 (de 2,15 m à 3,11m …",
  "seoDescription": "à vendre, 13008, Marseille, France"
}
