{
  "id": 1067593,
  "title": "",
  "slug": "mbvpa20009625-13005-marseille-france",
  "permalink": "https://www.immobiliere-pujol.fr/annonces/mbvpa20009625-13005-marseille-france/",
  "status": "closed",
  "date": "2025-05-20 20:10:46",
  "referenceAgence": "MBVPA20009625",
  "typeAnnonce": "V",
  "termine": "Terminé",
  "adresse": "13005, Marseille, France",
  "prix": 22500,
  "charges": 13,
  "honoraires": "0.00",
  "garantie": "0",
  "surface": 0,
  "surfaceTerrain": 0,
  "nbPieces": 0,
  "nbChambres": 0,
  "etage": "0",
  "nbEtages": "0",
  "gesNote": "A",
  "gesValeur": "0",
  "descriptif": "EXCLUSIVITE / place de parking situé 143 bd Baille 13005 Marseille.<br> Au 1er sous sol d'un immeuble récent, emplacement de parking pour 1 voiture. Accès par la rue des vertus.<br> Hauteur maximale 2m. Dimension de la place 2.69 x 5.75.<br> Mandat no6170 - honoraires à la charge du vendeur. Charges annuelles 160EUR - Taxe foncière 213EUR .Copropriété de 133lots principaux - pas de procédures à l'encontre du syndicat des copropriétaires.Les informations sur les risques auxquels ce bien est exposé sont disponibles sur le site Géorisques : www.georisques.gouv.frIMMOBILIERE PUJOL / Benoit Marin-Vicente 06 37 56 68 51",
  "photos": [
    "https://pub-a37eed540afe4dc9b4479da74ba265e1.r2.dev/2025/05/photo_ae917a80663f70a741025ca70de2cfbb-196.jpg",
    "https://immopujol.staticlbi.com/wa/images/biens/1/a78fa2be09d4df1bbc2460107fff2959/photo_ae917a80663f70a741025ca70de2cfbb.jpg",
    "https://immopujol.staticlbi.com/wa/images/biens/1/a78fa2be09d4df1bbc2460107fff2959/photo_bf76940f1ab9a5a8a20f1180405abea2.png",
    "https://immopujol.staticlbi.com/wa/images/biens/1/a78fa2be09d4df1bbc2460107fff2959/photo_34d3dc1d46e18f308354eb8b6ebb5832.jpg"
  ],
  "contactAAfficher": "candice@immobiliere-pujol.fr",
  "seoTitle": "EXCLUSIVITE / place de parking situé 143 bd Baille 13005 Marseille. Au 1er sous sol d'un immeuble récent, emplacement de parking pour 1 voiture. Accès par la rue des vertus. Hauteur maximale 2m. D…",
  "seoDescription": "à vendre, 13005, Marseille, France"
}
