{
  "id": 390003,
  "title": "",
  "slug": "pvvap60005370-13008-marseille-france",
  "permalink": "https://www.immobiliere-pujol.fr/annonces/pvvap60005370-13008-marseille-france/",
  "status": "closed",
  "date": "2021-01-26 21:00:53",
  "referenceAgence": "PVVAP60005370",
  "typeAnnonce": "V",
  "termine": "Terminé",
  "adresse": "13008, Marseille, France",
  "prix": 210000,
  "charges": 0,
  "honoraires": "0.00",
  "garantie": "0",
  "surface": 46.31,
  "surfaceTerrain": 46.31,
  "nbPieces": 2,
  "nbChambres": 1,
  "etage": "7",
  "nbEtages": "0",
  "meuble": false,
  "dpeNote": "d",
  "dpeValeur": "151",
  "gesNote": "A",
  "gesValeur": "5",
  "typeChauffage": "10368",
  "libelle": "Appartement T2",
  "descriptif": "SOUS COMPROMIS - EXCLUSIVITE Grand type 2 de 53.3m2 dont 7m2 de terrasse, situé au 7e étage avec ascenseur et box double dans la résidence Le Cap Emeraude en plein 8ème arrondissement : 7 Boulevard Jacquand 13008. <br> Cet appartement très agréable est situé dans une résidence bien entretenue et calme. Il se compose : d'un séjour de 19m2 donnant sur une terrasse de 7m2, d'un coin cuisine semi ouvert sur le séjour, d'une chambre avec penderie, d'une salle de bains avec les toilettes séparés. <br> Un box double de 44m2 en sous-sol de la résidence complète ce bien et est inclus!<br> Situé à 3 mn à pieds de la place de Turcat Mery avec ses commerces et l'arrêt de bus. Rien n'est à prévoir !<br> Mandat de vente 5634, Charge mensuelles 77EUR, Foncier 1262EUR Pas de procédures à l'encontre du syndicat des copropriétaires. honoraires charge acquéreur (inclus dans le prix affiché)<br> IMMOBILIERE PUJOL 07 62 20 33 09 Visite virtuelle bientôt disponible pour cet appartement",
  "photos": [
    "https://www.immobiliere-pujol.fr/content/uploads/2021/01/photo_8934286a7ce41cc4d22e91c7bff1826a-100.jpg",
    "http://immopujol.staticlbi.com/wa/images/biens/1/bc6b14cc989f43a1732b964a4813af30/photo_8934286a7ce41cc4d22e91c7bff1826a.jpg",
    "http://immopujol.staticlbi.com/wa/images/biens/1/bc6b14cc989f43a1732b964a4813af30/photo_fc4a0d7fecc0a33031e7940a5fbc830b.jpg",
    "http://immopujol.staticlbi.com/wa/images/biens/1/bc6b14cc989f43a1732b964a4813af30/photo_83c987288240eb1e5285218f648bb597.jpg",
    "http://immopujol.staticlbi.com/wa/images/biens/1/bc6b14cc989f43a1732b964a4813af30/photo_33f92d6b491645c41bdf4f940aeea48d.jpg",
    "http://immopujol.staticlbi.com/wa/images/biens/1/bc6b14cc989f43a1732b964a4813af30/photo_798295b337b64c6a4d3fd63618d2f9a5.jpg",
    "http://immopujol.staticlbi.com/wa/images/biens/1/bc6b14cc989f43a1732b964a4813af30/photo_d551f98c5eb504c0c88a91674180a67b.jpg",
    "http://immopujol.staticlbi.com/wa/images/biens/1/bc6b14cc989f43a1732b964a4813af30/photo_2dcc143249af795eb310a0f057f46fd4.jpg",
    "http://immopujol.staticlbi.com/wa/images/biens/1/bc6b14cc989f43a1732b964a4813af30/photo_d520a01357eb243c1786c7473abce064.jpg"
  ],
  "contactAAfficher": "victorpellegrin@immobiliere-pujol.fr",
  "seoTitle": "SOUS COMPROMIS - EXCLUSIVITE Grand type 2 de 53.3m2 dont 7m2 de terrasse, situé au 7e étage avec ascenseur et box double dans la résidence Le Cap Emeraude en plein 8ème arrondissement : 7 Bouleva…",
  "seoDescription": "Appartement T2 à vendre, 13008, Marseille, France"
}
