{
  "id": 78778,
  "title": "B000436_DADD|B000436_29D8|B000436_47C4|B000436_5FC8|B000436_E28A",
  "slug": "v000436-vente-appartement-13008-marseille",
  "permalink": "https://www.immobiliere-pujol.fr/annonces/v000436-vente-appartement-13008-marseille/",
  "status": "closed",
  "date": "2017-11-23 11:45:39",
  "referenceAgence": "V000436",
  "typeAnnonce": "V",
  "typeBien": "Appartement",
  "termine": "Terminé",
  "adresse": "Paradis/prado, 13008, Marseille, France",
  "codePostal": "13008",
  "ville": "Marseille",
  "quartier": "PARADIS/PRADO",
  "prix": 75600.0,
  "charges": 79.0,
  "honoraires": "0.00",
  "surface": 19.0,
  "surfaceTerrain": 0.0,
  "nbPieces": 1,
  "nbChambres": 0,
  "nbSallesBain": 0,
  "nbSallesEau": 1,
  "nbWC": 1,
  "etage": "1",
  "nbEtages": "0",
  "meuble": false,
  "coupDeCoeur": false,
  "ascenseur": false,
  "cave": false,
  "parking": "0",
  "garage": "0",
  "terrasse": false,
  "piscine": true,
  "dpeNote": "d",
  "dpeValeur": "204",
  "gesNote": "e",
  "gesValeur": "48",
  "typeChauffage": "5120",
  "libelle": "Appartement 1 pièce",
  "descriptif": "Studio de 19m2 situé dans la résidence de standing les jardin de Thalassa 120 rue du Cdt ROLLAND 13008 résidence fermée avec gardien, piscine, tennis, espaces verts, parkings, proximité plages du Prado.<BR>Ce studio se compose d'une pièce de vie avec baie vitrée, un coin cuisine aménagée, placard, salle d'eau et wc. Charges de copropriétés 79/mois, foncier 380.<BR>Bien situé dans une copropriété de 8 lots - Mandat n°5294 Honoraires d'agence à la charge du vendeur.<BR>Possibilité d'acheter un deuxiéme studio juste à côté au même prix  -  mandat n°5295<BR>IMMOBILIERE PUJOL 0687950876",
  "contactAAfficher": "nicole@immobiliere-pujol.fr",
  "telephoneAAfficher": "04 91 37 38 21",
  "emailAAfficher": "nicole@immobiliere-pujol.fr",
  "seoTitle": "Appartement 1 pièce à vendre Paradis/prado, Marseille, France",
  "seoDescription": "<p>Studio de 19m2 situé dans la résidence de standing les jardin de Thalassa 120 rue du Cdt ROLLAND 13008 résidence fermée avec gardien, piscine, tennis, espa&#8230;</p>",
  "photos": [
    "https://www.immobiliere-pujol.fr/content/uploads/2017/11/B000436_DADD.jpg",
    "https://www.immobiliere-pujol.fr/content/uploads/2017/10/B000436_DADD.jpg",
    "https://www.immobiliere-pujol.fr/content/uploads/2017/10/B000436_E28A.jpg",
    "https://www.immobiliere-pujol.fr/content/uploads/2017/10/B000436_29D8.jpg",
    "https://www.immobiliere-pujol.fr/content/uploads/2017/10/B000436_47C4.jpg",
    "https://www.immobiliere-pujol.fr/content/uploads/2017/10/B000436_5FC8.jpg"
  ]
}