{
  "id": 54944,
  "title": "",
  "slug": "v000430-vente-appartement-13008-marseille",
  "permalink": "https://www.immobiliere-pujol.fr/annonces/v000430-vente-appartement-13008-marseille/",
  "status": "publish",
  "date": "2017-10-04 07:45:25",
  "referenceAgence": "V000430|V000430|V000430",
  "typeBien": "Appartement|Appartement|Appartement",
  "termine": "Ouverte",
  "adresse": "Saint-giniez, 13008, Marseille, France|Saint-giniez, 13008, Marseille, France|Saint-giniez, 13008, Marseille, France",
  "codePostal": "13008|13008|13008",
  "ville": "Marseille|Marseille|Marseille",
  "quartier": "SAINT-GINIEZ|SAINT-GINIEZ|SAINT-GINIEZ",
  "honoraires": "0.00|0.00|0.00",
  "nbSallesEau": 0,
  "etage": "2|2|2",
  "meuble": false,
  "coupDeCoeur": false,
  "ascenseur": false,
  "cave": false,
  "parking": "0",
  "garage": "0",
  "terrasse": false,
  "piscine": false,
  "typeChauffage": "4096|4096|4096",
  "libelle": "Appartement 3 pièces|Appartement 3 pièces|Appartement 3 pièces",
  "descriptif": "<p>Prado/St Giniez, idélaement situé au calme et sans vis à vis, grand type 3 avec garage et cave dans une copropriété de standing fermée, sécurisée avec gardien en retrait du 2eme Prado. Cet appartement d'environ 83m², traversant, se trouve au 2e étage avec ascenseur et se compose : d'un hall d'entrée, d'un séjour et d'une cuisine aménagée donnant sur une terrasse au calme sur verdure et sans vis à vis de 11m², de deux chambres sans vis à vis dont une de plus de 14m² avec placards, d'une salle de bains, des toilettes séparées, de placards aménagés dans le couloir desservant l'espace nuit et bains. Appartement climatisé, porte blindée, chauffage et eaux collectives, cave et garage fermé. A moins de 5mn du métro Rond Point du Prado, 150m des bus et des commerces de quartier Mazargues/St Giniez.<br />\nAppartement situé dans une copropriété avec ravalement de façade effectué et chaudières collectives neuves. Pas de procédure à l'encontre du syndicat des copropriétaires.<br />\nMandat de vente 5288, honoraires d'agence à la charge du vendeur, Foncier 2186, charges mensuelles 287.<br />\nIMMOBILIERE PUJOL 06 79 02 72 29</p>|<p>Prado/St Giniez, idélaement situé au calme et sans vis à vis, grand type 3 avec garage et cave dans une copropriété de standing fermée, sécurisée avec gardien en retrait du 2eme Prado. Cet appartement d'environ 83m², traversant, se trouve au 2e étage avec ascenseur et se compose : d'un hall d'entrée, d'un séjour et d'une cuisine aménagée donnant sur une terrasse au calme sur verdure et sans vis à vis de 11m², de deux chambres sans vis à vis dont une de plus de 14m² avec placards, d'une salle de bains, des toilettes séparées, de placards aménagés dans le couloir desservant l'espace nuit et bains. Appartement climatisé, porte blindée, chauffage et eaux collectives, cave et garage fermé. A moins de 5mn du métro Rond Point du Prado, 150m des bus et des commerces de quartier Mazargues/St Giniez.<br />\nAppartement situé dans une copropriété avec ravalement de façade effectué et chaudières collectives neuves. Pas de procédure à l'encontre du syndicat des copropriétaires.<br />\nMandat de vente 5288, honoraires d'agence à la charge du vendeur, Foncier 2186, charges mensuelles 287.<br />\nIMMOBILIERE PUJOL 06 79 02 72 29</p>|<p>Prado/St Giniez, idélaement situé au calme et sans vis à vis, grand type 3 avec garage et cave dans une copropriété de standing fermée, sécurisée avec gardien en retrait du 2eme Prado. Cet appartement d'environ 83m², traversant, se trouve au 2e étage avec ascenseur et se compose : d'un hall d'entrée, d'un séjour et d'une cuisine aménagée donnant sur une terrasse au calme sur verdure et sans vis à vis de 11m², de deux chambres sans vis à vis dont une de plus de 14m² avec placards, d'une salle de bains, des toilettes séparées, de placards aménagés dans le couloir desservant l'espace nuit et bains. Appartement climatisé, porte blindée, chauffage et eaux collectives, cave et garage fermé. A moins de 5mn du métro Rond Point du Prado, 150m des bus et des commerces de quartier Mazargues/St Giniez.<br />\nAppartement situé dans une copropriété avec ravalement de façade effectué et chaudières collectives neuves. Pas de procédure à l'encontre du syndicat des copropriétaires.<br />\nMandat de vente 5288, honoraires d'agence à la charge du vendeur, Foncier 2186, charges mensuelles 287.<br />\nIMMOBILIERE PUJOL 06 79 02 72 29</p>",
  "telephoneAAfficher": "04.91.37.33.55|04.91.37.33.55|04.91.37.33.55",
  "emailAAfficher": "caroline@immobiliere-pujol.fr|caroline@immobiliere-pujol.fr|caroline@immobiliere-pujol.fr",
  "seoTitle": "Appartement 3 pièces à vendre Saint-giniez, Marseille, France",
  "seoDescription": "Prado/St Giniez, idélaement situé au calme et sans vis à vis, grand type 3 avec garage et cave dans une copropriété de standing fermée, sécurisée avec gard&#8230;"
}
